carveme/__init__.py
carveme/config.cfg
carveme/cli/__init__.py
carveme/cli/benchmark.py
carveme/cli/build_universe.py
carveme/cli/carve.py
carveme/cli/curate_universe.py
carveme/cli/gapfill.py
carveme/cli/merge_community.py
carveme/data/benchmark/media_db.tsv
carveme/data/benchmark/biolog/bsub/biolog_carbon.tsv
carveme/data/benchmark/biolog/bsub/biolog_nitrogen.tsv
carveme/data/benchmark/biolog/bsub/biolog_phosphorus.tsv
carveme/data/benchmark/biolog/bsub/biolog_sulfur.tsv
carveme/data/benchmark/biolog/ecol/biolog_carbon.tsv
carveme/data/benchmark/biolog/ecol/biolog_nitrogen.tsv
carveme/data/benchmark/biolog/ecol/biolog_phosphorus.tsv
carveme/data/benchmark/biolog/ecol/biolog_sulfur.tsv
carveme/data/benchmark/biolog/paer/biolog_carbon.tsv
carveme/data/benchmark/biolog/rsol/biolog_carbon.tsv
carveme/data/benchmark/biolog/rsol/biolog_nitrogen.tsv
carveme/data/benchmark/biolog/rsol/biolog_phosphorus.tsv
carveme/data/benchmark/biolog/rsol/biolog_sulfur.tsv
carveme/data/benchmark/biolog/sone/biolog_carbon.tsv
carveme/data/benchmark/biolog/sone/biolog_nitrogen.tsv
carveme/data/benchmark/essentiality/bsub.tsv
carveme/data/benchmark/essentiality/ecol.tsv
carveme/data/benchmark/essentiality/mgen.tsv
carveme/data/benchmark/essentiality/paer.tsv
carveme/data/benchmark/essentiality/sone.tsv
carveme/data/benchmark/fasta/Bsubtilis_168.faa
carveme/data/benchmark/fasta/Bsubtilis_168.tsv
carveme/data/benchmark/fasta/Ecoli_K12_MG1655.faa
carveme/data/benchmark/fasta/Ecoli_K12_MG1655.tsv
carveme/data/benchmark/fasta/M_genitalium_G37.faa
carveme/data/benchmark/fasta/M_genitalium_G37.tsv
carveme/data/benchmark/fasta/Paeruginosa_PAO1.faa
carveme/data/benchmark/fasta/Paeruginosa_PAO1.tsv
carveme/data/benchmark/fasta/Rsolanacearum_GMI1000.faa
carveme/data/benchmark/fasta/Rsolanacearum_GMI1000.tsv
carveme/data/benchmark/fasta/Soneidensis_MR1.faa
carveme/data/benchmark/fasta/Soneidensis_MR1.tsv
carveme/data/benchmark/models/bsub.xml
carveme/data/benchmark/models/ecol.xml
carveme-1.6.6.dist-info/licenses/LICENSE
carveme-1.6.6.dist-info/METADATA
carveme-1.6.6.dist-info/WHEEL
carveme-1.6.6.dist-info/entry_points.txt
carveme-1.6.6.dist-info/top_level.txt
carveme-1.6.6.dist-info/RECORD
