Metadata-Version: 2.4
Name: carveme
Version: 1.6.6
Summary: CarveMe: automated metabolic model reconstruction
Home-page: https://github.com/cdanielmachado/carveme
Author: Daniel Machado
Author-email: cdanielmachado@gmail.com
License: Apache Software License 2.0
Keywords: carveme
Classifier: Development Status :: 5 - Production/Stable
Classifier: Environment :: Console
Classifier: Intended Audience :: Science/Research
Classifier: Topic :: Scientific/Engineering :: Bio-Informatics
Classifier: Programming Language :: Python :: 3.8
Classifier: Programming Language :: Python :: 3.9
Classifier: Programming Language :: Python :: 3.10
Classifier: Programming Language :: Python :: 3.11
Classifier: Programming Language :: Python :: 3.12
Classifier: Programming Language :: Python :: 3.13
Classifier: License :: OSI Approved :: Apache Software License
License-File: LICENSE
Requires-Dist: reframed>=1.5.4
Requires-Dist: pandas>=2.0
Dynamic: author
Dynamic: author-email
Dynamic: classifier
Dynamic: description
Dynamic: home-page
Dynamic: keywords
Dynamic: license
Dynamic: license-file
Dynamic: requires-dist
Dynamic: summary
